glassnode_python/__init__.py
glassnode_python/client.py
glassnode_python/metrics.py
glassnode_python/utils.py
glassnode_python-0.3.2.dist-info/licenses/LICENSE
glassnode_python-0.3.2.dist-info/METADATA
glassnode_python-0.3.2.dist-info/WHEEL
glassnode_python-0.3.2.dist-info/top_level.txt
glassnode_python-0.3.2.dist-info/RECORD
