Metadata-Version: 2.4
Name: glassnode-python
Version: 0.3.2
Summary: Glassnode API client that mimics the yfinance download experience.
Author: Leev1s
License:                     GNU GENERAL PUBLIC LICENSE
Project-URL: Homepage, https://github.com/Leev1s/glassnode-python
Project-URL: Source, https://github.com/Leev1s/glassnode-python
Keywords: glassnode,crypto,api,pandas
Classifier: Development Status :: 3 - Alpha
Classifier: Intended Audience :: Developers
Classifier: Intended Audience :: Financial and Insurance Industry
Classifier: License :: OSI Approved :: GNU General Public License v3 (GPLv3)
Classifier: Programming Language :: Python
Classifier: Programming Language :: Python :: 3
Classifier: Programming Language :: Python :: 3.9
Classifier: Programming Language :: Python :: 3.10
Classifier: Programming Language :: Python :: 3.11
Classifier: Programming Language :: Python :: 3.12
Classifier: Topic :: Office/Business :: Financial
Requires-Python: >=3.9
License-File: LICENSE
Requires-Dist: pandas>=1.5
Requires-Dist: requests>=2.31
Requires-Dist: python-dotenv>=1.0
Provides-Extra: test
Requires-Dist: pytest>=7.4; extra == "test"
Provides-Extra: viz
Requires-Dist: plotly>=5.24; extra == "viz"
Dynamic: license-file
